paid_ai_client-0.4.8.dist-info/licenses/LICENSE
paid_client/__init__.py
paid_client/core.py
paid_client/models/__init__.py
paid_client/models/account.py
paid_client/models/agent.py
paid_client/models/contact.py
paid_client/models/order.py
paid_client/models/signal.py
paid_ai_client-0.4.8.dist-info/METADATA
paid_ai_client-0.4.8.dist-info/WHEEL
paid_ai_client-0.4.8.dist-info/top_level.txt
paid_ai_client-0.4.8.dist-info/RECORD
