Metadata-Version: 2.4
Name: Paid.ai-Client
Version: 0.4.8
Summary: A package to interact with the Paid API.
Home-page: https://github.com/AgentPaid/ap-client
Author: Paid.ai
Author-email: raj@agentpaid.ai
Classifier: Programming Language :: Python :: 3
Classifier: License :: OSI Approved :: MIT License
Classifier: Operating System :: OS Independent
Classifier: Development Status :: 3 - Alpha
Requires-Python: >=3.6
License-File: LICENSE
Requires-Dist: requests>=2.0.0
Requires-Dist: python-dateutil>=2.8.2
Dynamic: author
Dynamic: author-email
Dynamic: classifier
Dynamic: description
Dynamic: description-content-type
Dynamic: home-page
Dynamic: license-file
Dynamic: requires-dist
Dynamic: requires-python
Dynamic: summary
